DLToolsF/__init__.py
DLToolsF/log_utils.py
DLToolsF/od_utils.py
DLToolsF/web/index.html
DLToolsF/web/show.py
DLToolsF/web/css/main.css
DLToolsF/web/css/viewer.css
DLToolsF/web/css/dist/viewer.css
DLToolsF/web/examples/custom-title.html
DLToolsF/web/examples/custom-toolbar.html
DLToolsF/web/examples/dynamic-viewer.html
DLToolsF/web/examples/moving-range-limit.html
DLToolsF/web/examples/viewer-in-modal.html
DLToolsF/web/js/main.js
DLToolsF/web/js/viewer.js
DLToolsF-0.0.5.dist-info/LICENSE
DLToolsF-0.0.5.dist-info/METADATA
DLToolsF-0.0.5.dist-info/WHEEL
DLToolsF-0.0.5.dist-info/top_level.txt
DLToolsF-0.0.5.dist-info/RECORD
