Metadata-Version: 2.1
Name: DLToolsF
Version: 0.0.5
Summary: None
Author: Joyphy
Author-email: joyphy@Joyphy.com
Classifier: Programming Language :: Python :: 3
Classifier: License :: OSI Approved :: Apache Software License
Classifier: Operating System :: OS Independent
Requires-Python: >=3.6
License-File: LICENSE
Requires-Dist: tornado
Requires-Dist: pillow
Requires-Dist: opencv-python
Requires-Dist: numpy
